CHANGES.rst
CONTRIBUTORS.rst
MANIFEST.in
README.rst
setup.py
cpskin/__init__.py
cpskin.agenda.egg-info/PKG-INFO
cpskin.agenda.egg-info/SOURCES.txt
cpskin.agenda.egg-info/dependency_links.txt
cpskin.agenda.egg-info/not-zip-safe
cpskin.agenda.egg-info/requires.txt
cpskin.agenda.egg-info/top_level.txt
cpskin/agenda/__init__.py
cpskin/agenda/adapters.py
cpskin/agenda/configure.zcml
cpskin/agenda/dates.py
cpskin/agenda/interfaces.py
cpskin/agenda/overrides.zcml
cpskin/agenda/profiles.zcml
cpskin/agenda/setuphandlers.py
cpskin/agenda/testing.py
cpskin/agenda/testing.zcml
cpskin/agenda/upgrades.py
cpskin/agenda/behaviors/__init__.py
cpskin/agenda/behaviors/configure.zcml
cpskin/agenda/behaviors/related_contacts.py
cpskin/agenda/behaviors/schedule.py
cpskin/agenda/browser/__init__.py
cpskin/agenda/browser/configure.zcml
cpskin/agenda/browser/event_booking.pt
cpskin/agenda/browser/event_booking.py
cpskin/agenda/browser/event_summary.pt
cpskin/agenda/browser/event_summary.py
cpskin/agenda/browser/resources/eventbooking.css
cpskin/agenda/browser/resources/eventbooking.js
cpskin/agenda/faceted/__init__.py
cpskin/agenda/faceted/configure.zcml
cpskin/agenda/faceted/views/__init__.py
cpskin/agenda/faceted/views/configure.zcml
cpskin/agenda/faceted/views/preview-event.pt
cpskin/agenda/faceted/views/preview-events.pt
cpskin/agenda/faceted/views/view-agenda-item.pt
cpskin/agenda/faceted/views/view-agenda-ungrouped-item.pt
cpskin/agenda/faceted/views/view-agenda-ungrouped.pt
cpskin/agenda/faceted/views/view-agenda.pt
cpskin/agenda/faceted/views/view.py
cpskin/agenda/faceted/widgets/__init__.py
cpskin/agenda/faceted/widgets/configure.zcml
cpskin/agenda/faceted/widgets/daterange/__init__.py
cpskin/agenda/faceted/widgets/daterange/configure.zcml
cpskin/agenda/faceted/widgets/daterange/widget.py
cpskin/agenda/faceted/widgets/simpledate/__init__.py
cpskin/agenda/faceted/widgets/simpledate/configure.zcml
cpskin/agenda/faceted/widgets/simpledate/edit.css
cpskin/agenda/faceted/widgets/simpledate/edit.js
cpskin/agenda/faceted/widgets/simpledate/view.css
cpskin/agenda/faceted/widgets/simpledate/view.js
cpskin/agenda/faceted/widgets/simpledate/widget.pt
cpskin/agenda/faceted/widgets/simpledate/widget.py
